{
  "name": "phase2_resnet18_seed41",
  "timestamp": "2026-03-06T21:10:45.323540",
  "hyperparams": {
    "model": "resnet18",
    "seed": 41,
    "epochs": 1,
    "batch_size": 32,
    "learning_rate": 0.0003,
    "weight_decay": 0.0001,
    "scheduler": "cosine",
    "patience": 7,
    "class_weighting": "inverse_frequency",
    "class_weights": [
      0.5389464497566223,
      0.7991541624069214,
      5.262354850769043,
      0.7968708872795105,
      0.7968708872795105,
      0.5007267594337463,
      0.374620258808136,
      0.7968708872795105,
      0.4175221621990204,
      0.8375518918037415,
      0.44984644651412964,
      0.47554099559783936,
      0.5674563646316528,
      0.24846751987934113,
      2.1372015476226807
    ],
    "pretrained": true,
    "amp_requested": false,
    "amp_active": false
  },
  "metrics": {
    "test_accuracy": 0.912467700258398,
    "test_f1_macro": 0.8906619287922468,
    "elapsed_seconds": 4080.6683138589997
  },
  "environment": {
    "python_version": "3.12.12 (main, Oct 10 2025, 08:52:57) [GCC 11.4.0]",
    "python_executable": "/usr/bin/python3",
    "platform": "Linux-6.6.113+-x86_64-with-glibc2.35",
    "pytorch_version": "2.9.1+cu128",
    "cuda_available": false,
    "cuda_version": null,
    "gpu_name": null,
    "gpu_memory_gb": null
  },
  "artifacts": {
    "split_manifest": {
      "timestamp": "2026-03-06T21:10:45.337171",
      "seed": 42,
      "label_column": "class_label",
      "git_commit": "92998e1fd8dc0a56d1ffc44113a27cbef26496fc",
      "splits": {
        "train": {
          "path": "CSV/plantvillage_train.csv",
          "exists": true,
          "sha256": "908e0e0d1f4bda4384f1e3050e7a9e5ae7e55d0904a6f3b991a6aed69ed2e9d3",
          "rows": 14446,
          "label_counts": {
            "0": 1035,
            "1": 698,
            "10": 1240,
            "11": 1173,
            "12": 983,
            "13": 2245,
            "14": 261,
            "2": 106,
            "3": 700,
            "4": 700,
            "5": 1114,
            "6": 1489,
            "7": 700,
            "8": 1336,
            "9": 666
          }
        },
        "val": {
          "path": "CSV/plantvillage_val.csv",
          "exists": true,
          "sha256": "cba29d9c92c73430c661ad38168cd9644025633f0af67e7f79ad2c412adb04f5",
          "rows": 3096,
          "label_counts": {
            "0": 222,
            "1": 150,
            "10": 265,
            "11": 252,
            "12": 210,
            "13": 482,
            "14": 56,
            "2": 23,
            "3": 150,
            "4": 150,
            "5": 238,
            "6": 319,
            "7": 150,
            "8": 286,
            "9": 143
          }
        },
        "test": {
          "path": "CSV/plantvillage_test.csv",
          "exists": true,
          "sha256": "7377cfcf78f42ba6dee73ef40cc0ad7a409c1e224a48de33d956d374bcdccf55",
          "rows": 3096,
          "label_counts": {
            "0": 221,
            "1": 149,
            "10": 266,
            "11": 251,
            "12": 211,
            "13": 481,
            "14": 56,
            "2": 23,
            "3": 150,
            "4": 150,
            "5": 239,
            "6": 319,
            "7": 150,
            "8": 287,
            "9": 143
          }
        }
      }
    },
    "split_manifest_file": {
      "path": "results/split_manifests/latest_split_manifest.json",
      "exists": true,
      "sha256": "f455a0fc6c9f5bbdabcfcbffcececc2a04ab77c8f09c97deed7d950b848b972b",
      "size_bytes": 2063,
      "modified_time": "2026-03-06T17:56:21.892586"
    },
    "metrics_file": {
      "path": "results/phase2/runs/resnet18/seed_41/metrics.json",
      "exists": true,
      "sha256": "3d16e67360b10515fb6223d8c7b86bf50e19515600dd3603c0d7842e3615ab7f",
      "size_bytes": 5121,
      "modified_time": "2026-03-06T21:10:45.323014"
    },
    "confusion_matrix_json_file": {
      "path": "results/phase2/runs/resnet18/seed_41/confusion_matrix.json",
      "exists": true,
      "sha256": "03367967e393a6f82993908f998b7ea7d968b1f2015847e60e2924b0f74fd248",
      "size_bytes": 2753,
      "modified_time": "2026-03-06T21:10:44.895980"
    },
    "confusion_matrix_png_file": {
      "path": "results/phase2/runs/resnet18/seed_41/confusion_matrix.png",
      "exists": true,
      "sha256": "72340cd95ddfc4fec84ff7fa53294237c4ab27eabc8821357f569017e026150f",
      "size_bytes": 33192,
      "modified_time": "2026-03-06T21:10:45.292012"
    },
    "model_checkpoint_file": {
      "path": "models/phase2/resnet18/seed_41/best.pth",
      "exists": true,
      "sha256": "4dbc4f81f0481b19883ea6514c4a977cfeaf01cefcf3b95c918d090d8e5ed527",
      "size_bytes": 44807435,
      "modified_time": "2026-03-06T21:10:44.841976"
    }
  },
  "git_commit": "92998e1fd8dc0a56d1ffc44113a27cbef26496fc",
  "notes": "Phase 2 benchmark run"
}